transcribe.py
whisper_clipboard-0.2.1.dist-info/LICENSE
whisper_clipboard-0.2.1.dist-info/METADATA
whisper_clipboard-0.2.1.dist-info/WHEEL
whisper_clipboard-0.2.1.dist-info/entry_points.txt
whisper_clipboard-0.2.1.dist-info/top_level.txt
whisper_clipboard-0.2.1.dist-info/RECORD
