Metadata-Version: 2.1
Name: whisper-clipboard
Version: 0.2.1
Summary: A basic TUI for transcribing audio to your clipboard using OpenAI's whisper models.
Home-page: http://github.com/data-stepper/whisper-clipboard
Author: Bent Mueller
Author-email: bentmuller.ai@gmail.com
Classifier: License :: OSI Approved :: MIT License
Classifier: Programming Language :: Python :: 3.8
Classifier: Programming Language :: Python :: 3.9
Classifier: Programming Language :: Python :: 3.10
License-File: LICENSE
Requires-Dist: openai-whisper
Requires-Dist: sounddevice
Requires-Dist: pyperclip
Requires-Dist: black
Requires-Dist: prompt-toolkit
